gitplots.py
gitplots-0.1.0.data/scripts/gitplots.py
gitplots-0.1.0.dist-info/METADATA
gitplots-0.1.0.dist-info/RECORD
gitplots-0.1.0.dist-info/WHEEL
gitplots-0.1.0.dist-info/top_level.txt
