Metadata-Version: 2.1
Name: gitplots
Version: 0.1.0
Summary: Plots from git logs
Home-page: http://github.com/juseg/gitplots
Author: Julien Seguinot
Author-email: seguinot@vaw.baug.ethz.ch
License: gpl-3.0
Platform: UNKNOWN
Requires-Dist: matplotlib
Requires-Dist: pandas
